delaunay_triangulation_and_its_dual_2d/__init__.py
delaunay_triangulation_and_its_dual_2d/_version.py
delaunay_triangulation_and_its_dual_2d/delaunay.py
delaunay_triangulation_and_its_dual_2d/exceptions.py
delaunay_triangulation_and_its_dual_2d/geometry/__init__.py
delaunay_triangulation_and_its_dual_2d/geometry/bounding_box_2d.py
delaunay_triangulation_and_its_dual_2d/geometry/centroid.py
delaunay_triangulation_and_its_dual_2d/geometry/circumcircle.py
delaunay_triangulation_and_its_dual_2d/util/__init__.py
delaunay_triangulation_and_its_dual_2d/util/scipy_spatial_mocked.py
delaunay_triangulation_and_its_dual_2d-0.1.6.dist-info/LICENSE
delaunay_triangulation_and_its_dual_2d-0.1.6.dist-info/METADATA
delaunay_triangulation_and_its_dual_2d-0.1.6.dist-info/WHEEL
delaunay_triangulation_and_its_dual_2d-0.1.6.dist-info/top_level.txt
delaunay_triangulation_and_its_dual_2d-0.1.6.dist-info/RECORD
