Metadata-Version: 2.1
Name: delaunay-triangulation-and-its-dual-2d
Version: 0.1.6
License: MIT License
Project-URL: Homepage, https://github.com/dailyideas/delaunay-triangulation-and-its-dual-2d
Classifier: Programming Language :: Python :: 3
Requires-Python: >=3.8
License-File: LICENSE
Requires-Dist: matplotlib
Requires-Dist: numpy
Requires-Dist: scipy >=0.12.0
Provides-Extra: dev
Requires-Dist: black ; extra == 'dev'
Provides-Extra: dist
Requires-Dist: build ; extra == 'dist'
Requires-Dist: twine ; extra == 'dist'
Provides-Extra: test
Requires-Dist: coverage ; extra == 'test'
Requires-Dist: matplotlib ; extra == 'test'
Requires-Dist: pytest ; extra == 'test'
Requires-Dist: tox ; extra == 'test'
